MANIFEST.in
README.rst
setup.py
django_zonecache/__init__.py
django_zonecache.egg-info/PKG-INFO
django_zonecache.egg-info/SOURCES.txt
django_zonecache.egg-info/dependency_links.txt
django_zonecache.egg-info/not-zip-safe
django_zonecache.egg-info/requires.txt
django_zonecache.egg-info/top_level.txt