Metadata-Version: 1.1
Name: django-zonecache
Version: 0.2.2
Summary: Small library to add support for cache zones to Django cache
Home-page: https://github.com/ailabs/django-zone-cache/
Author: Michael van Tellingen
Author-email: m.vantellingen@auto-interactive.nl
License: MIT
Platform: UNKNOWN
Classifier: Development Status :: 4 - Beta
Classifier: Environment :: Web Environment
Classifier: Framework :: Django
Classifier: Intended Audience :: Developers
Classifier: License :: OSI Approved :: MIT License
Classifier: Operating System :: OS Independent
Classifier: Programming Language :: Python
Classifier: Topic :: Software Development
